{
  "projects": [
    {
      "id": 1,
      "title": "Work",
      "goal": "Win",
      "deadline": "2026-02-14"
    }
  ],
  "areas": [
    {
      "id": 1,
      "title": "Inbox"
    },
    {
      "id": 2,
      "title": "Work"
    }
  ],
  "resources": [],
  "archives": [],
  "tasks": [
    {
      "id": 1,
      "title": "Test 1",
      "priority": "medium",
      "parent_type": "area",
      "parent_id": 1
    },
    {
      "id": 2,
      "title": "Get groceries",
      "priority": "medium",
      "parent_type": "area",
      "parent_id": 1
    },
    {
      "id": 3,
      "title": "get laid",
      "priority": "medium",
      "parent_type": "area",
      "parent_id": 1
    },
    {
      "id": 4,
      "title": "1",
      "priority": "medium",
      "parent_type": "area",
      "parent_id": 1
    },
    {
      "id": 5,
      "title": "Verify",
      "priority": "medium",
      "parent_type": "area",
      "parent_id": 1
    },
    {
      "id": 6,
      "title": "Test",
      "priority": "medium",
      "parent_type": "area",
      "parent_id": 1
    },
    {
      "id": 7,
      "title": "2",
      "priority": "medium",
      "parent_type": "area",
      "parent_id": 2
    }
  ],
  "documents": [
    {
      "id": 1,
      "filename": "76724492f8d2_Death_House_Original1.pdf",
      "original_name": "Death House Original1.pdf",
      "uploaded_at": "2026-02-07T19:09:52.220768+00:00"
    }
  ],
  "document_links": [
    {
      "document_id": 1,
      "linked_type": "area",
      "linked_id": 1
    }
  ],
  "document_markups": []
}